mallsense_sdk/README.md
mallsense_sdk/__init__.py
mallsense_sdk/api.py
mallsense_sdk/exceptions.py
mallsense_sdk/http.py
mallsense_sdk/models.py
mallsense_sdk/py.typed
mallsense_sdk/utils.py
mallsense_sdk/__pycache__/__init__.cpython-312.pyc
mallsense_sdk/__pycache__/api.cpython-312.pyc
mallsense_sdk/__pycache__/http.cpython-312.pyc
mallsense_sdk/__pycache__/metrics.cpython-312.pyc
mallsense_sdk/__pycache__/models.cpython-312.pyc
mallsense_sdk/bills/__init__.py
mallsense_sdk/bills/bills.py
mallsense_sdk/bills/checks.py
mallsense_sdk/bills/connectors.py
mallsense_sdk/bills/corrections.py
mallsense_sdk/bills/jobs.py
mallsense_sdk/bills/pos.py
mallsense_sdk/bills/projects.py
mallsense_sdk/bills/responsibility.py
mallsense_sdk/bills/security.py
mallsense_sdk/bills/snapshots.py
mallsense_sdk/bills/status.py
mallsense_sdk/bills/status2tenant.py
mallsense_sdk/bills/tasks.py
mallsense_sdk/bills/tenants.py
mallsense_sdk/core/__init__.py
mallsense_sdk/core/metrics.py
mallsense_sdk/core/structure.py
mallsense_sdk/core/__pycache__/__init__.cpython-312.pyc
mallsense_sdk/core/__pycache__/metrics.cpython-312.pyc
mallsense_sdk/sales/__init__.py
mallsense_sdk/sales/snapshots.py
mallsense_sdk-0.3.0.dist-info/METADATA
mallsense_sdk-0.3.0.dist-info/WHEEL
mallsense_sdk-0.3.0.dist-info/top_level.txt
mallsense_sdk-0.3.0.dist-info/RECORD
