Metadata-Version: 2.4
Name: mallsense-sdk
Version: 0.3.0
Summary: Unified Python SDK for Mallsense (Core, Sales, Bills)
Author-email: MallSense <dev@example.com>
License: MIT
Project-URL: Homepage, https://gitlab.focustech.xyz/service.head/mallsense-sdk
Project-URL: Documentation, https://gitlab.focustech.xyz/service.head/mallsense-sdk/-/tree/main/docs
Project-URL: Source, https://gitlab.focustech.xyz/service.head/mallsense-sdk
Project-URL: Issues, https://gitlab.focustech.xyz/service.head/mallsense-sdk/-/issues
Classifier: Programming Language :: Python :: 3
Classifier: Programming Language :: Python :: 3.10
Classifier: Programming Language :: Python :: 3.11
Classifier: Programming Language :: Python :: 3.12
Classifier: Operating System :: OS Independent
Classifier: Intended Audience :: Developers
Classifier: Topic :: Software Development :: Libraries :: Python Modules
Classifier: Typing :: Typed
Classifier: License :: OSI Approved :: MIT License
Requires-Python: >=3.8
Requires-Dist: requests<3,>=2.31
Requires-Dist: python-dotenv<2,>=1.0
Requires-Dist: pytz<2026,>=2023.3
Requires-Dist: python-dateutil<3,>=2.8.2
Requires-Dist: pandas<3,>=2
Requires-Dist: pydantic<3,>=2.3
